setup.py
bin/chardet2
chardet/__init__.py
chardet/big5freq.py
chardet/big5prober.py
chardet/chardistribution.py
chardet/charsetgroupprober.py
chardet/charsetprober.py
chardet/codingstatemachine.py
chardet/constants.py
chardet/escprober.py
chardet/escsm.py
chardet/eucjpprober.py
chardet/euckrfreq.py
chardet/euckrprober.py
chardet/euctwfreq.py
chardet/euctwprober.py
chardet/gb2312freq.py
chardet/gb2312prober.py
chardet/hebrewprober.py
chardet/jisfreq.py
chardet/jpcntx.py
chardet/langbulgarianmodel.py
chardet/langcyrillicmodel.py
chardet/langgreekmodel.py
chardet/langhebrewmodel.py
chardet/langhungarianmodel.py
chardet/langthaimodel.py
chardet/latin1prober.py
chardet/mbcharsetprober.py
chardet/mbcsgroupprober.py
chardet/mbcssm.py
chardet/sbcharsetprober.py
chardet/sbcsgroupprober.py
chardet/sjisprober.py
chardet/test.py
chardet/universaldetector.py
chardet/utf8prober.py
chardet2.egg-info/PKG-INFO
chardet2.egg-info/SOURCES.txt
chardet2.egg-info/dependency_links.txt
chardet2.egg-info/top_level.txt