Metadata-Version: 1.0
Name: chardet2
Version: 2.0.3
Summary: Character encoding auto-detection in Python 3
Home-page: https://github.com/byroot/chardet
Author: Mark Pilgrim
Author-email: mark@diveintomark.com
License: LGPL
Platform: Independent
Classifier: Development Status :: 4 - Beta
Classifier: Environment :: Other Environment
Classifier: Intended Audience :: Developers
Classifier: License :: OSI Approved :: GNU Library or Lesser General Public License (LGPL)
Classifier: Operating System :: OS Independent
Classifier: Programming Language :: Python
Classifier: Topic :: Software Development :: Libraries :: Python Modules
Classifier: Topic :: Text Processing :: Linguistic
